{
  "results": [
    {
      "adult": false,
      "backdrop_path": "/4woSOUD0equAYzvwhWBHIJDCM88.jpg",
      "genre_ids": [28, 27, 53],
      "id": 1096197,
      "original_language": "en",
      "original_title": "No Way Up",
      "overview": "Characters from different backgrounds are thrown together when the plane they're travelling on crashes into the Pacific Ocean. A nightmare fight for survival ensues with the air supply running out and dangers creeping in from all sides.",
      "popularity": 434.011,
      "poster_path": "/hu40Uxp9WtpL34jv3zyWLb5zEVY.jpg",
      "release_date": "2024-01-18",
      "title": "No Way Up",
      "video": false,
      "vote_average": 6.346,
      "vote_count": 379
    },
    {
      "adult": false,
      "backdrop_path": "/5cCfqeUH2f5Gnu7Lh9xepY9TB6x.jpg",
      "genre_ids": [14, 12, 35],
      "id": 967847,
      "original_language": "en",
      "original_title": "Ghostbusters: Frozen Empire",
      "overview": "The Spengler family returns to where it all started – the iconic New York City firehouse – to team up with the original Ghostbusters, who've developed a top-secret research lab to take busting ghosts to the next level. But when the discovery of an ancient artifact unleashes an evil force, Ghostbusters new and old must join forces to protect their home and save the world from a second Ice Age.",
      "popularity": 447.565,
      "poster_path": "/6faYaQyiBPhqAizldJKq21mIVaE.jpg",
      "release_date": "2024-03-20",
      "title": "Ghostbusters: Frozen Empire",
      "video": false,
      "vote_average": 6.486,
      "vote_count": 243
    },
    {
      "adult": false,
      "backdrop_path": "/iqqMJwvPlovftBfdHVrpP2B1IxE.jpg",
      "genre_ids": [28, 80, 53, 18],
      "id": 551115,
      "original_language": "nl",
      "original_title": "Penoza: The Final Chapter",
      "overview": "The Black Widow is not dead ... Drug Queen Carmen van Walraven is hiding in Canada and leads an anonymous life there. One evening a colleague is harassed and Carmen helps her. In self-defense, she kills the perpetrator, is arrested and extradited to the Netherlands. While her children are in shock that their mother is still alive, there are also some people who still have to settle something with Carmen. Everyone is again dragged into an emotional rollercoaster. Carmen will now have deal with her past to save her family.",
      "popularity": 392.676,
      "poster_path": "/ba1NlageLgbxOPLXjX0qX7HDBTc.jpg",
      "release_date": "2019-11-28",
      "title": "Penoza: The Final Chapter",
      "video": false,
      "vote_average": 6.9,
      "vote_count": 42
    },
    {
      "adult": false,
      "backdrop_path": "/rKmp0vm6PNaFA0g1bzM70eyWJ6I.jpg",
      "genre_ids": [28],
      "id": 873972,
      "original_language": "en",
      "original_title": "Hunters",
      "overview": "As John T. Wrecker continues his task of protecting a group of refugees from a virus, the threat of something new and even more dangerous grows ever closer in the form of monstrous mutants.",
      "popularity": 354.447,
      "poster_path": "/3UKlVa1CBeQkRksHV5OfFTO52qd.jpg",
      "release_date": "2021-09-13",
      "title": "Hunters",
      "video": false,
      "vote_average": 6.353,
      "vote_count": 16
    },
    {
      "adult": false,
      "backdrop_path": "/9wJO4MBzkqgUZemLTGEsgUbYyP6.jpg",
      "genre_ids": [878, 9648, 53, 28],
      "id": 720321,
      "original_language": "en",
      "original_title": "Breathe",
      "overview": "Air-supply is scarce in the near future, forcing a mother and daughter to fight for survival when two strangers arrive desperate for an oxygenated haven.",
      "popularity": 602.7,
      "poster_path": "/wTW2t8ocWDlHns8I7vQxuqkyK58.jpg",
      "release_date": "2024-04-04",
      "title": "Breathe",
      "video": false,
      "vote_average": 5.328,
      "vote_count": 32
    },
    {
      "adult": false,
      "backdrop_path": "/wxYBMcxFIJai9AaZr6XAOKZTfxY.jpg",
      "genre_ids": [35],
      "id": 1229913,
      "original_language": "es",
      "original_title": "室友",
      "overview": "Vivi is a young writer who is forced to find a roommate to pay the mortgage on her apartment. What she does not suspect is that Roy, the supposed perfect partner she found, has a peculiar lifestyle: he never pays rent.",
      "popularity": 425.916,
      "poster_path": "/zaRzz2BxjxIVb7ja0gSedj1Hn1E.jpg",
      "release_date": "2024-01-18",
      "title": "The Roommate",
      "video": false,
      "vote_average": 6.725,
      "vote_count": 20
    },
    {
      "adult": false,
      "backdrop_path": "/nb3xI8XI3w4pMVZ38VijbsyBqP4.jpg",
      "genre_ids": [18, 36],
      "id": 872585,
      "original_language": "en",
      "original_title": "Oppenheimer",
      "overview": "The story of J. Robert Oppenheimer's role in the development of the atomic bomb during World War II.",
      "popularity": 431.357,
      "poster_path": "/8Gxv8gSFCU0XGDykEGv7zR1n2ua.jpg",
      "release_date": "2023-07-19",
      "title": "Oppenheimer",
      "video": false,
      "vote_average": 8.11,
      "vote_count": 7677
    },
    {
      "adult": false,
      "backdrop_path": "/deLWkOLZmBNkm8p16igfapQyqeq.jpg",
      "genre_ids": [14, 28, 12],
      "id": 763215,
      "original_language": "en",
      "original_title": "Damsel",
      "overview": "A young woman's marriage to a charming prince turns into a fierce fight for survival when she's offered up as a sacrifice to a fire-breathing dragon.",
      "popularity": 367.676,
      "poster_path": "/AgHbB9DCE9aE57zkHjSmseszh6e.jpg",
      "release_date": "2024-03-07",
      "title": "Damsel",
      "video": false,
      "vote_average": 7.139,
      "vote_count": 1596
    },
    {
      "adult": false,
      "backdrop_path": "/oBIQDKcqNxKckjugtmzpIIOgoc4.jpg",
      "genre_ids": [28, 53, 10752],
      "id": 969492,
      "original_language": "en",
      "original_title": "Land of Bad",
      "overview": "When a Delta Force special ops mission goes terribly wrong, Air Force drone pilot Reaper has 48 hours to remedy what has devolved into a wild rescue operation. With no weapons and no communication other than the drone above, the ground mission suddenly becomes a full-scale battle when the team is discovered by the enemy.",
      "popularity": 357.438,
      "poster_path": "/h3jYanWMEJq6JJsCopy1h7cT2Hs.jpg",
      "release_date": "2024-01-25",
      "title": "Land of Bad",
      "video": false,
      "vote_average": 7.193,
      "vote_count": 563
    },
    {
      "adult": false,
      "backdrop_path": "/mIBG74mhGEJnBubhYLkCtvplcNr.jpg",
      "genre_ids": [27],
      "id": 437342,
      "original_language": "en",
      "original_title": "The First Omen",
      "overview": "When a young American woman is sent to Rome to begin a life of service to the church, she encounters a darkness that causes her to question her own faith and uncovers a terrifying conspiracy that hopes to bring about the birth of evil incarnate.",
      "popularity": 364.92,
      "poster_path": "/hil2ResSCwP95JweZVJsZ5CbZdc.jpg",
      "release_date": "2024-04-03",
      "title": "The First Omen",
      "video": false,
      "vote_average": 6.722,
      "vote_count": 99
    },
    {
      "adult": false,
      "backdrop_path": "/lP0G6f00CjOKdRECyGrT0kaMSrL.jpg",
      "genre_ids": [18],
      "id": 383634,
      "original_language": "ja",
      "original_title": "肉体の門",
      "overview": "Prostitutes in burnt out Tokyo ghetto of post-WWII Japan peddle their flesh and save one-third of their money for a proposed dancehall to be named Paradise. The hookers live in a bombed-out building, but they accept the precarious situation with typical resolve.",
      "popularity": 395.101,
      "poster_path": "/raNbLci95MJ3L3dMnG7L7bD37lY.jpg",
      "release_date": "1988-04-09",
      "title": "Carmen 1945",
      "video": false,
      "vote_average": 4.0,
      "vote_count": 2
    },
    {
      "adult": false,
      "backdrop_path": "/xvk5AhfhgQcTuaCQyq3XqAnhEma.jpg",
      "genre_ids": [28, 12, 35],
      "id": 848538,
      "original_language": "en",
      "original_title": "Argylle",
      "overview": "When the plots of reclusive author Elly Conway's fictional espionage novels begin to mirror the covert actions of a real-life spy organization, quiet evenings at home become a thing of the past. Accompanied by her cat Alfie and Aiden, a cat-allergic spy, Elly races across the world to stay one step ahead of the killers as the line between Conway's fictional world and her real one begins to blur.",
      "popularity": 323.012,
      "poster_path": "/siduVKgOnABO4WH4lOwPQwaGwJp.jpg",
      "release_date": "2024-01-31",
      "title": "Argylle",
      "video": false,
      "vote_average": 6.2,
      "vote_count": 889
    },
    {
      "adult": false,
      "backdrop_path": "/bQS43HSLZzMjZkcHJz4fGc7fNdz.jpg",
      "genre_ids": [878, 10749, 35],
      "id": 792307,
      "original_language": "en",
      "original_title": "Poor Things",
      "overview": "Brought back to life by an unorthodox scientist, a young woman runs off with a debauched lawyer on a whirlwind adventure across the continents. Free from the prejudices of her times, she grows steadfast in her purpose to stand for equality and liberation.",
      "popularity": 355.57,
      "poster_path": "/kCGlIMHnOm8JPXq3rXM6c5wMxcT.jpg",
      "release_date": "2023-12-07",
      "title": "Poor Things",
      "video": false,
      "vote_average": 7.817,
      "vote_count": 3101
    },
    {
      "adult": false,
      "backdrop_path": "/qwK9soQmmJ7kRdjLZVXblw3g7AQ.jpg",
      "genre_ids": [28, 12, 53, 80],
      "id": 7451,
      "original_language": "en",
      "original_title": "xXx",
      "overview": "Xander Cage is your standard adrenaline junkie with no fear and a lousy attitude. When the US Government \"recruits\" him to go on a mission, he's not exactly thrilled. His mission: to gather information on an organization that may just be planning the destruction of the world, led by the nihilistic Yorgi.",
      "popularity": 308.709,
      "poster_path": "/xeEw3eLeSFmJgXZzmF2Efww0q3s.jpg",
      "release_date": "2002-08-09",
      "title": "xXx",
      "video": false,
      "vote_average": 5.927,
      "vote_count": 4009
    },
    {
      "adult": false,
      "backdrop_path": "/ou8DQx4F0JBrgYglAucYJyE6PZZ.jpg",
      "genre_ids": [27],
      "id": 1022128,
      "original_language": "en",
      "original_title": "Don't Look at the Demon",
      "overview": "A spiritual medium leads a paranormal investigative TV crew to a haunted home only to discover that the evil spirit she’s facing holds the key to her troubled past.",
      "popularity": 268.537,
      "poster_path": "/wSfQ0JEjoeVeVCQR3bmMLl6xBHK.jpg",
      "release_date": "2022-09-29",
      "title": "Don't Look at the Demon",
      "video": false,
      "vote_average": 5.5,
      "vote_count": 15
    },
    {
      "adult": false,
      "backdrop_path": "/oFAukXiMPrwLpbulGmB5suEZlrm.jpg",
      "genre_ids": [28, 12, 878, 14, 18],
      "id": 624091,
      "original_language": "id",
      "original_title": "Sri Asih",
      "overview": "Alana discover the truth about her origin: she’s not an ordinary human being. She may be the gift for humanity and become its protector as Sri Asih. Or a destruction, if she can’t control her anger.",
      "popularity": 306.113,
      "poster_path": "/wShcJSKMFg1Dy1yq7kEZuay6pLS.jpg",
      "release_date": "2022-11-17",
      "title": "Sri Asih",
      "video": false,
      "vote_average": 6.297,
      "vote_count": 79
    },
    {
      "adult": false,
      "backdrop_path": "/yyFc8Iclt2jxPmLztbP617xXllT.jpg",
      "genre_ids": [35, 10751, 14],
      "id": 787699,
      "original_language": "en",
      "original_title": "Wonka",
      "overview": "Willy Wonka – chock-full of ideas and determined to change the world one delectable bite at a time – is proof that the best things in life begin with a dream, and if you’re lucky enough to meet Willy Wonka, anything is possible.",
      "popularity": 345.67,
      "poster_path": "/qhb1qOilapbapxWQn9jtRCMwXJF.jpg",
      "release_date": "2023-12-06",
      "title": "Wonka",
      "video": false,
      "vote_average": 7.2,
      "vote_count": 2840
    },
    {
      "adult": false,
      "backdrop_path": "/inJjDhCjfhh3RtrJWBmmDqeuSYC.jpg",
      "genre_ids": [28, 878, 53],
      "id": 399566,
      "original_language": "en",
      "original_title": "Godzilla vs. Kong",
      "overview": "In a time when monsters walk the Earth, humanity’s fight for its future sets Godzilla and Kong on a collision course that will see the two most powerful forces of nature on the planet collide in a spectacular battle for the ages.",
      "popularity": 291.097,
      "poster_path": "/pgqgaUx1cJb5oZQQ5v0tNARCeBp.jpg",
      "release_date": "2021-03-24",
      "title": "Godzilla vs. Kong",
      "video": false,
      "vote_average": 7.623,
      "vote_count": 9602
    },
    {
      "adult": false,
      "backdrop_path": "/bWIIWhnaoWx3FTVXv6GkYDv3djL.jpg",
      "genre_ids": [878, 27, 28],
      "id": 940721,
      "original_language": "ja",
      "original_title": "ゴジラ-1.0",
      "overview": "Postwar Japan is at its lowest point when a new crisis emerges in the form of a giant monster, baptized in the horrific power of the atomic bomb.",
      "popularity": 304.346,
      "poster_path": "/hkxxMIGaiCTmrEArK7J56JTKUlB.jpg",
      "release_date": "2023-11-03",
      "title": "Godzilla Minus One",
      "video": false,
      "vote_average": 7.836,
      "vote_count": 488
    },
    {
      "adult": false,
      "backdrop_path": "/4Ep2KivIBUZbkS7kHjW7Qywnhhj.jpg",
      "genre_ids": [28],
      "id": 1049948,
      "original_language": "en",
      "original_title": "Vikings: Battle of Heirs",
      "overview": "A young Viking must come to terms with the realization that he may be the King's son, who was switched at birth, but not before others try to take his rightful place.",
      "popularity": 273.691,
      "poster_path": "/87goLbbqrJqAxqDS5cBsik1zKT.jpg",
      "release_date": "2023-04-28",
      "title": "Vikings: Battle of Heirs",
      "video": false,
      "vote_average": 6.5,
      "vote_count": 24
    }
  ],
  "total_pages": 43612,
  "total_results": 872239
}
